djadmin/__init__.py
djadmin/admin.py
djadmin/apps.py
djadmin/colors.py
djadmin/forms.py
djadmin/middleware.py
djadmin/mixins.py
djadmin/models.py
djadmin/settings.py
djadmin/sidebar.py
djadmin/signals.py
djadmin/tests.py
djadmin/urls.py
djadmin/util.py
djadmin/views.py
djadmin/migrations/0001_initial.py
djadmin/migrations/0002_auto_20170128_1519.py
djadmin/migrations/0003_auto_20170324_0011.py
djadmin/migrations/0004_auto_20181103_1950.py
djadmin/migrations/0005_auto_20181103_2030.py
djadmin/migrations/__init__.py
djadmin/templatetags/__init__.py
djadmin/templatetags/base.py
djadmin/templatetags/compat.py
djadmin/templatetags/custom.py
djadmin/templatetags/djadmin.py
djadmin/templatetags/djadmin_form.py
djadmin/templatetags/djadmin_inline_form.py
djadmin/templatetags/material_admin.py
djadmin/templatetags/material_form.py
djadmin/templatetags/material_form_internal.py
djadmin/templatetags/user_agents.py
djadmin_ok-1.1.9.dist-info/LICENSE
djadmin_ok-1.1.9.dist-info/METADATA
djadmin_ok-1.1.9.dist-info/WHEEL
djadmin_ok-1.1.9.dist-info/top_level.txt
djadmin_ok-1.1.9.dist-info/RECORD
